flask_file_upload/__init__.py
flask_file_upload/_config.py
flask_file_upload/_exceptions.py
flask_file_upload/_model_utils.py
flask_file_upload/column.py
flask_file_upload/file_upload.py
flask_file_upload/file_utils.py
flask_file_upload/model.py
flask_file_upload-0.2.1.dist-info/LICENSE.md
flask_file_upload-0.2.1.dist-info/METADATA
flask_file_upload-0.2.1.dist-info/WHEEL
flask_file_upload-0.2.1.dist-info/top_level.txt
flask_file_upload-0.2.1.dist-info/RECORD
