Metadata-Version: 2.1
Name: flask-file-upload
Version: 0.2.1
Summary: Library that works with Flask & SqlAlchemy to store files in your database and server.
Home-page: https://github.com/joegasewicz/Flask-File-Upload
Author: Joe Gasewicz
Author-email: joegasewicz@gmail.com
License: UNKNOWN
Platform: UNKNOWN
Classifier: Programming Language :: Python :: 3
Classifier: Programming Language :: Python :: 3.6
Classifier: Programming Language :: Python :: 3.7
Classifier: Programming Language :: Python :: 3.8
Classifier: Programming Language :: Python :: 3.9
Classifier: License :: OSI Approved :: GNU General Public License v3 or later (GPLv3+)
Classifier: Operating System :: OS Independent
License-File: LICENSE.md
